{
  "version": "5.0.1",
  "flags": {},
  "shapes": [
    {
      "label": "building",
      "points": [
        [
          502,
          107
        ],
        [
          493,
          137
        ],
        [
          512,
          142
        ],
        [
          512,
          111
        ],
        [
          508,
          110
        ]
      ],
      "group_id": 6,
      "shape_type": "polygon",
      "flags": {}
    },
    {
      "label": "building",
      "points": [
        [
          414,
          390
        ],
        [
          403,
          423
        ],
        [
          512,
          458
        ],
        [
          512,
          421
        ],
        [
          441,
          399
        ]
      ],
      "group_id": 21,
      "shape_type": "polygon",
      "flags": {}
    },
    {
      "label": "building",
      "points": [
        [
          438,
          319
        ],
        [
          428,
          354
        ],
        [
          512,
          379
        ],
        [
          512,
          340
        ],
        [
          463,
          326
        ]
      ],
      "group_id": 21,
      "shape_type": "polygon",
      "flags": {}
    },
    {
      "label": "building",
      "points": [
        [
          394,
          464
        ],
        [
          384,
          498
        ],
        [
          427,
          512
        ],
        [
          499,
          512
        ],
        [
          504,
          499
        ],
        [
          419,
          472
        ]
      ],
      "group_id": 21,
      "shape_type": "polygon",
      "flags": {}
    },
    {
      "label": "building",
      "points": [
        [
          462,
          249
        ],
        [
          452,
          283
        ],
        [
          512,
          302
        ],
        [
          512,
          264
        ],
        [
          485,
          256
        ]
      ],
      "group_id": 21,
      "shape_type": "polygon",
      "flags": {}
    },
    {
      "label": "building",
      "points": [
        [
          512,
          211
        ],
        [
          512,
          173
        ],
        [
          486,
          165
        ],
        [
          474,
          200
        ],
        [
          500,
          208
        ]
      ],
      "group_id": 21,
      "shape_type": "polygon",
      "flags": {}
    },
    {
      "label": "building",
      "points": [
        [
          408,
          506
        ],
        [
          384,
          498
        ],
        [
          394,
          464
        ],
        [
          419,
          472
        ],
        [
          431,
          432
        ],
        [
          403,
          423
        ],
        [
          414,
          390
        ],
        [
          441,
          399
        ],
        [
          453,
          361
        ],
        [
          428,
          354
        ],
        [
          438,
          319
        ],
        [
          463,
          326
        ],
        [
          475,
          290
        ],
        [
          452,
          283
        ],
        [
          462,
          249
        ],
        [
          485,
          256
        ],
        [
          500,
          208
        ],
        [
          474,
          200
        ],
        [
          374,
          512
        ],
        [
          406,
          512
        ]
      ],
      "group_id": 6,
      "shape_type": "polygon",
      "flags": {}
    },
    {
      "label": "building",
      "points": [
        [
          37,
          313
        ],
        [
          36,
          288
        ],
        [
          38,
          285
        ],
        [
          0,
          262
        ],
        [
          0,
          296
        ],
        [
          13,
          304
        ],
        [
          0,
          326
        ],
        [
          0,
          394
        ],
        [
          44,
          317
        ]
      ],
      "group_id": 21,
      "shape_type": "polygon",
      "flags": {}
    },
    {
      "label": "building",
      "points": [
        [
          169,
          189
        ],
        [
          158,
          177
        ],
        [
          175,
          160
        ],
        [
          164,
          149
        ],
        [
          173,
          140
        ],
        [
          142,
          108
        ],
        [
          110,
          138
        ],
        [
          122,
          150
        ],
        [
          111,
          161
        ],
        [
          128,
          179
        ],
        [
          124,
          183
        ],
        [
          148,
          209
        ],
        [
          164,
          193
        ]
      ],
      "group_id": 9,
      "shape_type": "polygon",
      "flags": {}
    },
    {
      "label": "building",
      "points": [
        [
          178,
          198
        ],
        [
          169,
          189
        ],
        [
          164,
          193
        ],
        [
          189,
          219
        ],
        [
          179,
          229
        ],
        [
          195,
          245
        ],
        [
          206,
          235
        ],
        [
          218,
          247
        ],
        [
          253,
          214
        ],
        [
          221,
          180
        ],
        [
          213,
          188
        ],
        [
          201,
          176
        ]
      ],
      "group_id": 9,
      "shape_type": "polygon",
      "flags": {}
    },
    {
      "label": "building",
      "points": [
        [
          385,
          202
        ],
        [
          428,
          106
        ],
        [
          376,
          83
        ],
        [
          333,
          178
        ],
        [
          376,
          198
        ]
      ],
      "group_id": 12,
      "shape_type": "polygon",
      "flags": {}
    },
    {
      "label": "building",
      "points": [
        [
          333,
          178
        ],
        [
          289,
          220
        ],
        [
          319,
          252
        ],
        [
          376,
          198
        ]
      ],
      "group_id": 12,
      "shape_type": "polygon",
      "flags": {}
    },
    {
      "label": "building",
      "points": [
        [
          247,
          191
        ],
        [
          243,
          187
        ],
        [
          235,
          195
        ],
        [
          253,
          214
        ],
        [
          239,
          227
        ],
        [
          258,
          247
        ],
        [
          271,
          234
        ],
        [
          285,
          249
        ],
        [
          301,
          233
        ],
        [
          289,
          220
        ],
        [
          308,
          202
        ],
        [
          287,
          180
        ],
        [
          274,
          193
        ],
        [
          260,
          179
        ]
      ],
      "group_id": 9,
      "shape_type": "polygon",
      "flags": {}
    },
    {
      "label": "building",
      "points": [
        [
          289,
          472
        ],
        [
          292,
          462
        ],
        [
          305,
          466
        ],
        [
          337,
          367
        ],
        [
          323,
          363
        ],
        [
          319,
          351
        ],
        [
          322,
          340
        ],
        [
          306,
          335
        ],
        [
          297,
          362
        ],
        [
          302,
          363
        ],
        [
          305,
          374
        ],
        [
          282,
          444
        ],
        [
          278,
          443
        ],
        [
          271,
          466
        ]
      ],
      "group_id": 21,
      "shape_type": "polygon",
      "flags": {}
    },
    {
      "label": "building",
      "points": [
        [
          196,
          417
        ],
        [
          187,
          443
        ],
        [
          270,
          470
        ],
        [
          278,
          443
        ]
      ],
      "group_id": 21,
      "shape_type": "polygon",
      "flags": {}
    },
    {
      "label": "building",
      "points": [
        [
          219,
          308
        ],
        [
          211,
          332
        ],
        [
          298,
          359
        ],
        [
          306,
          335
        ]
      ],
      "group_id": 21,
      "shape_type": "polygon",
      "flags": {}
    },
    {
      "label": "building",
      "points": [
        [
          76,
          358
        ],
        [
          172,
          390
        ],
        [
          181,
          365
        ],
        [
          84,
          332
        ]
      ],
      "group_id": 21,
      "shape_type": "polygon",
      "flags": {}
    },
    {
      "label": "building",
      "points": [
        [
          52,
          443
        ],
        [
          148,
          473
        ],
        [
          156,
          450
        ],
        [
          59,
          420
        ]
      ],
      "group_id": 21,
      "shape_type": "polygon",
      "flags": {}
    },
    {
      "label": "building",
      "points": [
        [
          73,
          26
        ],
        [
          5,
          17
        ],
        [
          0,
          25
        ],
        [
          0,
          206
        ],
        [
          42,
          231
        ],
        [
          75,
          174
        ]
      ],
      "group_id": 9,
      "shape_type": "polygon",
      "flags": {}
    },
    {
      "label": "building",
      "points": [
        [
          240.0,
          512.0
        ],
        [
          240.0,
          492.0
        ],
        [
          153.0,
          491.0
        ],
        [
          153.0,
          511.0
        ],
        [
          240.0,
          512.0
        ]
      ],
      "group_id": 18,
      "shape_type": "polygon",
      "flags": {}
    },
    {
      "label": "building",
      "points": [
        [
          12.0,
          440.0
        ],
        [
          16.0,
          410.0
        ],
        [
          0.0,
          407.0
        ],
        [
          0.0,
          437.0
        ],
        [
          12.0,
          440.0
        ]
      ],
      "group_id": 9,
      "shape_type": "polygon",
      "flags": {}
    },
    {
      "label": "building",
      "points": [
        [
          102.0,
          512.0
        ],
        [
          102.0,
          491.0
        ],
        [
          29.0,
          491.0
        ],
        [
          29.0,
          511.0
        ],
        [
          102.0,
          512.0
        ]
      ],
      "group_id": 18,
      "shape_type": "polygon",
      "flags": {}
    },
    {
      "label": "building",
      "points": [
        [
          152.0,
          101.0
        ],
        [
          155.0,
          52.0
        ],
        [
          112.0,
          49.0
        ],
        [
          109.0,
          99.0
        ],
        [
          152.0,
          101.0
        ]
      ],
      "group_id": 3,
      "shape_type": "polygon",
      "flags": {}
    }
  ],
  "imagePath": "aggtbjreks.png",
  "imageData": null,
  "imageHeight": 512,
  "imageWidth": 512
}